Workbook

Sheet Inputs
A1: FlipPulse — Business Model Inputs
A2: Edit the shaded (yellow) cells. Everything else recomputes on the other sheets.
A4: REVENUE
A5: Startup fee per new customer | B5: 150
A6: Monthly subscription per customer | B6: 99
A7: Performance fee (% of customer monthly profit) | B7: 0.2
A8: Include performance fee in headline totals? (1=yes, 0=no) | B8: 0 | C8: Kept OFF by default — it's an illustrative upside, and needs compliance review.
A10: PERFORMANCE-FEE ASSUMPTIONS (illustrative — UNPROVEN)
A11: Avg funded balance per customer | B11: 2000 | C11: Your guess of the typical account size.
A12: Avg monthly net return per customer | B12: 0.05 | C12: The bot's real edge is unproven (paper mode by default). Adjust freely.
A14: GROWTH
A15: Monthly churn (% of active customers) | B15: 0.04
A17: RECURRING COSTS (monthly)
A18: Claude Max | B18: 100
A19: Railway base (Pro plan) | B19: 20
A20: Railway usage per active bot | B20: 5 | C20: Each customer = one always-on bot. ~$3–8/mo of usage each; tune to real bills.
A21: GitHub | B21: 0 | C21: Free covers unlimited private repos. Team is $4/user if you add staff.
A22: Misc software / tools (domain, email, etc.) | B22: 30
A24: PAYMENT PROCESSING (Stripe)
A25: Stripe % per charge | B25: 0.029
A26: Stripe fixed per charge | B26: 0.3
A27: Stripe Billing % (recurring) | B27: 0.007
A29: HARDWARE (capital expense — funded from profits)
A30: Mac mini (top spec, M4 Pro 48GB / 1TB) | B30: 2000
A31: Large curved monitor | B31: 1000
A32: Peripherals / desk setup | B32: 300
A33: Hardware total | B33: =B30+B31+B32
A34: Purchase in month (1–12) | B34: 5 | C34: Only sensible once cumulative profit covers it — see the Summary check.

Sheet Monthly Model
A1: FlipPulse — 12-Month Model
A2: Month | B2: Cust. start | C2: Cust. end | D2: Churned | E2: New | F2: Setup rev | G2: Subscription | H2: Perf fee* | I2: Total revenue | J2: Claude | K2: Railway | L2: GitHub+Misc | M2: Stripe fees | N2: Total OpEx | O2: Hardware capex | P2: Net profit | Q2: Cumulative
A3: 1 | B3: 0 | C3: 8 | D3: =B3*Inputs!$B$15 | E3: =C3-B3+D3 | F3: =E3*Inputs!$B$5 | G3: =((B3+C3)/2)*Inputs!$B$6 | H3: =((B3+C3)/2)*Inputs!$B$11*Inputs!$B$12*Inputs!$B$7*Inputs!$B$8 | I3: =F3+G3+H3 | J3: =Inputs!$B$18 | K3: =Inputs!$B$19+((B3+C3)/2)*Inputs!$B$20 | L3: =Inputs!$B$21+Inputs!$B$22 | M3: =E3*(Inputs!$B$25*Inputs!$B$5+Inputs!$B$26)+((B3+C3)/2)*(Inputs!$B$25*Inputs!$B$6+Inputs!$B$26+Inputs!$B$27*Inputs!$B$6)+H3*(Inputs!$B$25+Inputs!$B$27) | N3: =J3+K3+L3+M3 | O3: =IF(A3=Inputs!$B$34,Inputs!$B$33,0) | P3: =I3-N3-O3 | Q3: =P3
A4: 2 | B4: =C3 | C4: 20 | D4: =B4*Inputs!$B$15 | E4: =C4-B4+D4 | F4: =E4*Inputs!$B$5 | G4: =((B4+C4)/2)*Inputs!$B$6 | H4: =((B4+C4)/2)*Inputs!$B$11*Inputs!$B$12*Inputs!$B$7*Inputs!$B$8 | I4: =F4+G4+H4 | J4: =Inputs!$B$18 | K4: =Inputs!$B$19+((B4+C4)/2)*Inputs!$B$20 | L4: =Inputs!$B$21+Inputs!$B$22 | M4: =E4*(Inputs!$B$25*Inputs!$B$5+Inputs!$B$26)+((B4+C4)/2)*(Inputs!$B$25*Inputs!$B$6+Inputs!$B$26+Inputs!$B$27*Inputs!$B$6)+H4*(Inputs!$B$25+Inputs!$B$27) | N4: =J4+K4+L4+M4 | O4: =IF(A4=Inputs!$B$34,Inputs!$B$33,0) | P4: =I4-N4-O4 | Q4: =Q3+P4
A5: 3 | B5: =C4 | C5: 38 | D5: =B5*Inputs!$B$15 | E5: =C5-B5+D5 | F5: =E5*Inputs!$B$5 | G5: =((B5+C5)/2)*Inputs!$B$6 | H5: =((B5+C5)/2)*Inputs!$B$11*Inputs!$B$12*Inputs!$B$7*Inputs!$B$8 | I5: =F5+G5+H5 | J5: =Inputs!$B$18 | K5: =Inputs!$B$19+((B5+C5)/2)*Inputs!$B$20 | L5: =Inputs!$B$21+Inputs!$B$22 | M5: =E5*(Inputs!$B$25*Inputs!$B$5+Inputs!$B$26)+((B5+C5)/2)*(Inputs!$B$25*Inputs!$B$6+Inputs!$B$26+Inputs!$B$27*Inputs!$B$6)+H5*(Inputs!$B$25+Inputs!$B$27) | N5: =J5+K5+L5+M5 | O5: =IF(A5=Inputs!$B$34,Inputs!$B$33,0) | P5: =I5-N5-O5 | Q5: =Q4+P5
A6: 4 | B6: =C5 | C6: 60 | D6: =B6*Inputs!$B$15 | E6: =C6-B6+D6 | F6: =E6*Inputs!$B$5 | G6: =((B6+C6)/2)*Inputs!$B$6 | H6: =((B6+C6)/2)*Inputs!$B$11*Inputs!$B$12*Inputs!$B$7*Inputs!$B$8 | I6: =F6+G6+H6 | J6: =Inputs!$B$18 | K6: =Inputs!$B$19+((B6+C6)/2)*Inputs!$B$20 | L6: =Inputs!$B$21+Inputs!$B$22 | M6: =E6*(Inputs!$B$25*Inputs!$B$5+Inputs!$B$26)+((B6+C6)/2)*(Inputs!$B$25*Inputs!$B$6+Inputs!$B$26+Inputs!$B$27*Inputs!$B$6)+H6*(Inputs!$B$25+Inputs!$B$27) | N6: =J6+K6+L6+M6 | O6: =IF(A6=Inputs!$B$34,Inputs!$B$33,0) | P6: =I6-N6-O6 | Q6: =Q5+P6
A7: 5 | B7: =C6 | C7: 80 | D7: =B7*Inputs!$B$15 | E7: =C7-B7+D7 | F7: =E7*Inputs!$B$5 | G7: =((B7+C7)/2)*Inputs!$B$6 | H7: =((B7+C7)/2)*Inputs!$B$11*Inputs!$B$12*Inputs!$B$7*Inputs!$B$8 | I7: =F7+G7+H7 | J7: =Inputs!$B$18 | K7: =Inputs!$B$19+((B7+C7)/2)*Inputs!$B$20 | L7: =Inputs!$B$21+Inputs!$B$22 | M7: =E7*(Inputs!$B$25*Inputs!$B$5+Inputs!$B$26)+((B7+C7)/2)*(Inputs!$B$25*Inputs!$B$6+Inputs!$B$26+Inputs!$B$27*Inputs!$B$6)+H7*(Inputs!$B$25+Inputs!$B$27) | N7: =J7+K7+L7+M7 | O7: =IF(A7=Inputs!$B$34,Inputs!$B$33,0) | P7: =I7-N7-O7 | Q7: =Q6+P7
A8: 6 | B8: =C7 | C8: 100 | D8: =B8*Inputs!$B$15 | E8: =C8-B8+D8 | F8: =E8*Inputs!$B$5 | G8: =((B8+C8)/2)*Inputs!$B$6 | H8: =((B8+C8)/2)*Inputs!$B$11*Inputs!$B$12*Inputs!$B$7*Inputs!$B$8 | I8: =F8+G8+H8 | J8: =Inputs!$B$18 | K8: =Inputs!$B$19+((B8+C8)/2)*Inputs!$B$20 | L8: =Inputs!$B$21+Inputs!$B$22 | M8: =E8*(Inputs!$B$25*Inputs!$B$5+Inputs!$B$26)+((B8+C8)/2)*(Inputs!$B$25*Inputs!$B$6+Inputs!$B$26+Inputs!$B$27*Inputs!$B$6)+H8*(Inputs!$B$25+Inputs!$B$27) | N8: =J8+K8+L8+M8 | O8: =IF(A8=Inputs!$B$34,Inputs!$B$33,0) | P8: =I8-N8-O8 | Q8: =Q7+P8
A9: 7 | B9: =C8 | C9: 140 | D9: =B9*Inputs!$B$15 | E9: =C9-B9+D9 | F9: =E9*Inputs!$B$5 | G9: =((B9+C9)/2)*Inputs!$B$6 | H9: =((B9+C9)/2)*Inputs!$B$11*Inputs!$B$12*Inputs!$B$7*Inputs!$B$8 | I9: =F9+G9+H9 | J9: =Inputs!$B$18 | K9: =Inputs!$B$19+((B9+C9)/2)*Inputs!$B$20 | L9: =Inputs!$B$21+Inputs!$B$22 | M9: =E9*(Inputs!$B$25*Inputs!$B$5+Inputs!$B$26)+((B9+C9)/2)*(Inputs!$B$25*Inputs!$B$6+Inputs!$B$26+Inputs!$B$27*Inputs!$B$6)+H9*(Inputs!$B$25+Inputs!$B$27) | N9: =J9+K9+L9+M9 | O9: =IF(A9=Inputs!$B$34,Inputs!$B$33,0) | P9: =I9-N9-O9 | Q9: =Q8+P9
A10: 8 | B10: =C9 | C10: 190 | D10: =B10*Inputs!$B$15 | E10: =C10-B10+D10 | F10: =E10*Inputs!$B$5 | G10: =((B10+C10)/2)*Inputs!$B$6 | H10: =((B10+C10)/2)*Inputs!$B$11*Inputs!$B$12*Inputs!$B$7*Inputs!$B$8 | I10: =F10+G10+H10 | J10: =Inputs!$B$18 | K10: =Inputs!$B$19+((B10+C10)/2)*Inputs!$B$20 | L10: =Inputs!$B$21+Inputs!$B$22 | M10: =E10*(Inputs!$B$25*Inputs!$B$5+Inputs!$B$26)+((B10+C10)/2)*(Inputs!$B$25*Inputs!$B$6+Inputs!$B$26+Inputs!$B$27*Inputs!$B$6)+H10*(Inputs!$B$25+Inputs!$B$27) | N10: =J10+K10+L10+M10 | O10: =IF(A10=Inputs!$B$34,Inputs!$B$33,0) | P10: =I10-N10-O10 | Q10: =Q9+P10
A11: 9 | B11: =C10 | C11: 255 | D11: =B11*Inputs!$B$15 | E11: =C11-B11+D11 | F11: =E11*Inputs!$B$5 | G11: =((B11+C11)/2)*Inputs!$B$6 | H11: =((B11+C11)/2)*Inputs!$B$11*Inputs!$B$12*Inputs!$B$7*Inputs!$B$8 | I11: =F11+G11+H11 | J11: =Inputs!$B$18 | K11: =Inputs!$B$19+((B11+C11)/2)*Inputs!$B$20 | L11: =Inputs!$B$21+Inputs!$B$22 | M11: =E11*(Inputs!$B$25*Inputs!$B$5+Inputs!$B$26)+((B11+C11)/2)*(Inputs!$B$25*Inputs!$B$6+Inputs!$B$26+Inputs!$B$27*Inputs!$B$6)+H11*(Inputs!$B$25+Inputs!$B$27) | N11: =J11+K11+L11+M11 | O11: =IF(A11=Inputs!$B$34,Inputs!$B$33,0) | P11: =I11-N11-O11 | Q11: =Q10+P11
A12: 10 | B12: =C11 | C12: 330 | D12: =B12*Inputs!$B$15 | E12: =C12-B12+D12 | F12: =E12*Inputs!$B$5 | G12: =((B12+C12)/2)*Inputs!$B$6 | H12: =((B12+C12)/2)*Inputs!$B$11*Inputs!$B$12*Inputs!$B$7*Inputs!$B$8 | I12: =F12+G12+H12 | J12: =Inputs!$B$18 | K12: =Inputs!$B$19+((B12+C12)/2)*Inputs!$B$20 | L12: =Inputs!$B$21+Inputs!$B$22 | M12: =E12*(Inputs!$B$25*Inputs!$B$5+Inputs!$B$26)+((B12+C12)/2)*(Inputs!$B$25*Inputs!$B$6+Inputs!$B$26+Inputs!$B$27*Inputs!$B$6)+H12*(Inputs!$B$25+Inputs!$B$27) | N12: =J12+K12+L12+M12 | O12: =IF(A12=Inputs!$B$34,Inputs!$B$33,0) | P12: =I12-N12-O12 | Q12: =Q11+P12
A13: 11 | B13: =C12 | C13: 415 | D13: =B13*Inputs!$B$15 | E13: =C13-B13+D13 | F13: =E13*Inputs!$B$5 | G13: =((B13+C13)/2)*Inputs!$B$6 | H13: =((B13+C13)/2)*Inputs!$B$11*Inputs!$B$12*Inputs!$B$7*Inputs!$B$8 | I13: =F13+G13+H13 | J13: =Inputs!$B$18 | K13: =Inputs!$B$19+((B13+C13)/2)*Inputs!$B$20 | L13: =Inputs!$B$21+Inputs!$B$22 | M13: =E13*(Inputs!$B$25*Inputs!$B$5+Inputs!$B$26)+((B13+C13)/2)*(Inputs!$B$25*Inputs!$B$6+Inputs!$B$26+Inputs!$B$27*Inputs!$B$6)+H13*(Inputs!$B$25+Inputs!$B$27) | N13: =J13+K13+L13+M13 | O13: =IF(A13=Inputs!$B$34,Inputs!$B$33,0) | P13: =I13-N13-O13 | Q13: =Q12+P13
A14: 12 | B14: =C13 | C14: 500 | D14: =B14*Inputs!$B$15 | E14: =C14-B14+D14 | F14: =E14*Inputs!$B$5 | G14: =((B14+C14)/2)*Inputs!$B$6 | H14: =((B14+C14)/2)*Inputs!$B$11*Inputs!$B$12*Inputs!$B$7*Inputs!$B$8 | I14: =F14+G14+H14 | J14: =Inputs!$B$18 | K14: =Inputs!$B$19+((B14+C14)/2)*Inputs!$B$20 | L14: =Inputs!$B$21+Inputs!$B$22 | M14: =E14*(Inputs!$B$25*Inputs!$B$5+Inputs!$B$26)+((B14+C14)/2)*(Inputs!$B$25*Inputs!$B$6+Inputs!$B$26+Inputs!$B$27*Inputs!$B$6)+H14*(Inputs!$B$25+Inputs!$B$27) | N14: =J14+K14+L14+M14 | O14: =IF(A14=Inputs!$B$34,Inputs!$B$33,0) | P14: =I14-N14-O14 | Q14: =Q13+P14
A15: YEAR | F15: =SUM(F3:F14) | G15: =SUM(G3:G14) | H15: =SUM(H3:H14) | I15: =SUM(I3:I14) | J15: =SUM(J3:J14) | K15: =SUM(K3:K14) | L15: =SUM(L3:L14) | M15: =SUM(M3:M14) | ... P15: =SUM(P3:P14) | Q15: =Q14
A16: * Perf fee is illustrative (needs compliance review) and is OFF in totals unless Inputs!B8 = 1.

Sheet Summary
A1: FlipPulse — Summary
A3: QUARTERLY | B3: Q1 (m1-3) | C3: Q2 (m4-6) | D3: Q3 (m7-9) | E3: Q4 (m10-12)
A4: Revenue | B4: =SUM('Monthly Model'!I3:I5) | C4: =SUM('Monthly Model'!I6:I8) | D4: =SUM('Monthly Model'!I9:I11) | E4: =SUM('Monthly Model'!I12:I14)
A5: Operating costs | B5: =SUM('Monthly Model'!N3:N5) | C5: =SUM('Monthly Model'!N6:N8) | D5: =SUM('Monthly Model'!N9:N11) | E5: =SUM('Monthly Model'!N12:N14)
A6: Hardware capex | B6: =SUM('Monthly Model'!O3:O5) | C6: =SUM('Monthly Model'!O6:O8) | D6: =SUM('Monthly Model'!O9:O11) | E6: =SUM('Monthly Model'!O12:O14)
A7: Net profit | B7: =SUM('Monthly Model'!P3:P5) | C7: =SUM('Monthly Model'!P6:P8) | D7: =SUM('Monthly Model'!P9:P11) | E7: =SUM('Monthly Model'!P12:P14)
A10: ANNUAL (Year 1)
A11: Total revenue (contracted: setup + subscription) | B11: =SUM('Monthly Model'!I3:I14)
A12: Total operating costs | B12: =SUM('Monthly Model'!N3:N14)
A13: Total hardware capex | B13: =SUM('Monthly Model'!O3:O14)
A14: Net profit (Year 1) | B14: =SUM('Monthly Model'!P3:P14)
A15: Gross margin (rev − opex) / rev | B15: =(SUM('Monthly Model'!I3:I14)-SUM('Monthly Model'!N3:N14))/SUM('Monthly Model'!I3:I14)
A17: KEY METRICS
A18: Ending customers (month 12) | B18: ='Monthly Model'!C14
A19: Ending MRR (run-rate: customers × sub) | B19: ='Monthly Model'!C14*Inputs!$B$6
A20: Ending ARR (MRR × 12) | B20: ='Monthly Model'!C14*Inputs!$B$6*12
A21: Avg revenue / customer / month (m12) | B21: ='Monthly Model'!I14/(('Monthly Model'!B14+'Monthly Model'!C14)/2)
A22: Cumulative net profit (end of year) | B22: ='Monthly Model'!Q14
A24: HARDWARE CHECK
A25: Cumulative profit BEFORE hardware, at purchase month | B25: =SUMIF('Monthly Model'!$A$3:$A$14,"<="&Inputs!$B$34,'Monthly Model'!$P$3:$P$14)+SUMIF('Monthly Model'!$A$3:$A$14,"<="&Inputs!$B$34,'Monthly Model'!$O$3:$O$14)
A26: Hardware total | B26: =Inputs!$B$33
A27: Covered by profits? (should be TRUE) | B27: =IF(B25>=B26,"YES — funded from profit","NO — push purchase later")
A29: PERFORMANCE-FEE UPSIDE (illustrative, not in totals above)
A30: Annual performance-fee revenue (if it holds) | B30: =(SUMPRODUCT(('Monthly Model'!B3:B14+'Monthly Model'!C3:C14)/2))*Inputs!$B$11*Inputs!$B$12*Inputs!$B$7
A31: Total revenue INCL. perf-fee upside | B31: =SUM('Monthly Model'!I3:I14)+B30
A32: Net profit INCL. perf-fee upside | B32: =SUM('Monthly Model'!P3:P14)+B30
A33: Upside assumes every active customer nets Inputs!B12 per month on Inputs!B11 of capital. Unproven — treat as a ceiling, not a forecast.

Sheet Cost Notes
A1: FlipPulse — Cost Research & Sources (as of mid-2026)
A3: Item | B3: Figure used | C3: Notes / source
A4: Claude Max | B4: $100 / mo | C4: Max tier as specified. A $200/mo (higher-usage) tier also exists.
A5: Railway | B5: $20 base + ~$5/bot | C5: Pro plan is $20/mo incl. credits; usage billed per-minute. Each always-on bot is a small container (~$3–8/mo). Hobby is $5/mo incl. $5 usage. (docs.railway.com/pricing)
A6: GitHub | B6: $0 | C6: Free plan includes unlimited private repos. GitHub Team is $4/user/mo if you add collaborators. Copilot is separate ($0–$100/mo).
A7: Stripe | B7: 2.9% + $0.30, +0.7% | C7: Standard US card fee 2.9% + $0.30 per charge; Stripe Billing adds ~0.5–0.7% on recurring. No flat monthly fee on standard. (stripe.com/pricing, stripe.com/billing/pricing)
A8: Mac mini (top spec) | B8: ~$2,000 | C8: M4 Pro (14-core) starts ~$1,599 (2026 price rise); 48GB/1TB config lands near $2,000+. (apple.com/mac-mini)
A9: Large curved monitor | B9: ~$1,000 | C9: Premium 34" QD-OLED ultrawide ~$799 (e.g. Alienware AW3425DW); 49" super-ultrawide runs higher. (rtings.com, tomsguide.com)
A10: Peripherals / desk | B10: $300 | C10: Keyboard, mouse, cabling, desk odds & ends.
A12: These are defaults on the Inputs sheet — override any of them with your real bills.
